{"arxivId":null,"authors":[{"authorId":"2159885","name":"Yuchen Li","url":"https://www.semanticscholar.org/author/2159885"},{"authorId":"3232294","name":"Ju Fan","url":"https://www.semanticscholar.org/author/3232294"},{"authorId":"2712862","name":"Dongxiang Zhang","url":"https://www.semanticscholar.org/author/2712862"},{"authorId":"1688848","name":"Kian-Lee Tan","url":"https://www.semanticscholar.org/author/1688848"}],"citationVelocity":0,"citations":[{"arxivId":null,"authors":[{"authorId":"50875262","name":"Fan Zhou","url":"https://www.semanticscholar.org/author/50875262"},{"authorId":"1703617","name":"Lei Liu","url":"https://www.semanticscholar.org/author/1703617"},{"authorId":"2737830","name":"Kunpeng Zhang","url":"https://www.semanticscholar.org/author/2737830"},{"authorId":"1776969","name":"Goce Trajcevski","url":"https://www.semanticscholar.org/author/1776969"},{"authorId":"49388207","name":"Jin Wu","url":"https://www.semanticscholar.org/author/49388207"}],"doi":"10.1109/ACCESS.2019.2890826","isInfluential":false,"paperId":"9bf46f753b56344a120f5503e477f2f225789b30","title":"Predicting Topic Participation by Jointly Learning User Intrinsic and Extrinsic Preference","url":"https://www.semanticscholar.org/paper/9bf46f753b56344a120f5503e477f2f225789b30","venue":"IEEE Access","year":2019},{"arxivId":"1802.02254","authors":[{"authorId":"40187998","name":"Ping Zhang","url":"https://www.semanticscholar.org/author/40187998"},{"authorId":"39505779","name":"Zhifeng Bao","url":"https://www.semanticscholar.org/author/39505779"},{"authorId":"2159885","name":"Yuchen Li","url":"https://www.semanticscholar.org/author/2159885"},{"authorId":"23492509","name":"Guoliang Li","url":"https://www.semanticscholar.org/author/23492509"},{"authorId":"2760404","name":"Yipeng Zhang","url":"https://www.semanticscholar.org/author/2760404"},{"authorId":"1968724","name":"Zhiyong Peng","url":"https://www.semanticscholar.org/author/1968724"}],"doi":"10.1145/3219819.3219946","isInfluential":false,"paperId":"786f1d4e18d8c684c0c6bc61c86dfdd0c974822b","title":"Trajectory-driven Influential Billboard Placement","url":"https://www.semanticscholar.org/paper/786f1d4e18d8c684c0c6bc61c86dfdd0c974822b","venue":"KDD","year":2018},{"arxivId":"1903.08587","authors":[{"authorId":"8766005","name":"Xiangyu Ke","url":"https://www.semanticscholar.org/author/8766005"},{"authorId":"1725060","name":"Arijit Khan","url":"https://www.semanticscholar.org/author/1725060"},{"authorId":"1686755","name":"Mohammad S. Hasan","url":"https://www.semanticscholar.org/author/1686755"},{"authorId":"86972564","name":"Rojin Rezvansangsari","url":"https://www.semanticscholar.org/author/86972564"}],"doi":null,"isInfluential":false,"paperId":"007c73fdc03d288c204a683506c602c345fbdf7f","title":"Budgeted Reliability Maximization in Uncertain Graphs","url":"https://www.semanticscholar.org/paper/007c73fdc03d288c204a683506c602c345fbdf7f","venue":"ArXiv","year":2019},{"arxivId":null,"authors":[{"authorId":"3232294","name":"Ju Fan","url":"https://www.semanticscholar.org/author/3232294"},{"authorId":"10713620","name":"Jiarong Qiu","url":"https://www.semanticscholar.org/author/10713620"},{"authorId":"2159885","name":"Yuchen Li","url":"https://www.semanticscholar.org/author/2159885"},{"authorId":"9413192","name":"Qingfei Meng","url":"https://www.semanticscholar.org/author/9413192"},{"authorId":"2712862","name":"Dongxiang Zhang","url":"https://www.semanticscholar.org/author/2712862"},{"authorId":"23492509","name":"Guoliang Li","url":"https://www.semanticscholar.org/author/23492509"},{"authorId":"1688848","name":"Kian-Lee Tan","url":"https://www.semanticscholar.org/author/1688848"},{"authorId":"1688063","name":"Xiaoyong Du","url":"https://www.semanticscholar.org/author/1688063"}],"doi":"10.1109/ICDE.2018.00178","isInfluential":true,"paperId":"f86608f284942efdc7dd6e13f5eba64c9360c72f","title":"OCTOPUS: An Online Topic-Aware Influence Analysis System for Social Networks","url":"https://www.semanticscholar.org/paper/f86608f284942efdc7dd6e13f5eba64c9360c72f","venue":"2018 IEEE 34th International Conference on Data Engineering (ICDE)","year":2018},{"arxivId":null,"authors":[{"authorId":"2159885","name":"Yuchen Li","url":"https://www.semanticscholar.org/author/2159885"},{"authorId":"3232294","name":"Ju Fan","url":"https://www.semanticscholar.org/author/3232294"},{"authorId":"2220456","name":"Yanhao Wang","url":"https://www.semanticscholar.org/author/2220456"},{"authorId":"46934259","name":"Kian-Lee Tan","url":"https://www.semanticscholar.org/author/46934259"}],"doi":"10.1109/TKDE.2018.2807843","isInfluential":false,"paperId":"de5e4c789209dfed61d427675e20ccf7362b9375","title":"Influence Maximization on Social Graphs: A Survey","url":"https://www.semanticscholar.org/paper/de5e4c789209dfed61d427675e20ccf7362b9375","venue":"IEEE Transactions on Knowledge and Data Engineering","year":2018},{"arxivId":"1901.10109","authors":[{"authorId":"2220456","name":"Yanhao Wang","url":"https://www.semanticscholar.org/author/2220456"},{"authorId":"2159885","name":"Yuchen Li","url":"https://www.semanticscholar.org/author/2159885"},{"authorId":"1688848","name":"Kian-Lee Tan","url":"https://www.semanticscholar.org/author/1688848"}],"doi":"10.5441/002/edbt.2019.17","isInfluential":false,"paperId":"023689074e3786269e31ba2a9e993213bf043141","title":"Semantic and Influence aware k-Representative Queries over Social Streams","url":"https://www.semanticscholar.org/paper/023689074e3786269e31ba2a9e993213bf043141","venue":"EDBT","year":2019},{"arxivId":null,"authors":[{"authorId":"2220456","name":"Yanhao Wang","url":"https://www.semanticscholar.org/author/2220456"},{"authorId":"2159885","name":"Yuchen Li","url":"https://www.semanticscholar.org/author/2159885"},{"authorId":"3232294","name":"Ju Fan","url":"https://www.semanticscholar.org/author/3232294"},{"authorId":"1688848","name":"Kian-Lee Tan","url":"https://www.semanticscholar.org/author/1688848"}],"doi":"10.1145/3230871","isInfluential":false,"paperId":"e1b21974e1266b0e0440b742a2d10d2478f0a897","title":"Location-aware Influence Maximization over Dynamic Social Streams","url":"https://www.semanticscholar.org/paper/e1b21974e1266b0e0440b742a2d10d2478f0a897","venue":"ACM Trans. Inf. Syst.","year":2018},{"arxivId":"1608.04474","authors":[{"authorId":"1725060","name":"Arijit Khan","url":"https://www.semanticscholar.org/author/1725060"},{"authorId":"1705764","name":"Francesco Bonchi","url":"https://www.semanticscholar.org/author/1705764"},{"authorId":"1794262","name":"Francesco Gullo","url":"https://www.semanticscholar.org/author/1794262"},{"authorId":"3451938","name":"Andreas Nufer","url":"https://www.semanticscholar.org/author/3451938"}],"doi":"10.1109/TKDE.2018.2816653","isInfluential":true,"paperId":"1a0a8cc5db722dc9cd18a8a3d205924c5b1ed54d","title":"Conditional Reliability in Uncertain Graphs","url":"https://www.semanticscholar.org/paper/1a0a8cc5db722dc9cd18a8a3d205924c5b1ed54d","venue":"IEEE Transactions on Knowledge and Data Engineering","year":2018},{"arxivId":"1702.01586","authors":[{"authorId":"2220456","name":"Yanhao Wang","url":"https://www.semanticscholar.org/author/2220456"},{"authorId":"48868170","name":"Qi Fan","url":"https://www.semanticscholar.org/author/48868170"},{"authorId":"2159885","name":"Yuchen Li","url":"https://www.semanticscholar.org/author/2159885"},{"authorId":"1688848","name":"Kian-Lee Tan","url":"https://www.semanticscholar.org/author/1688848"}],"doi":"10.14778/3067421.3067429","isInfluential":false,"paperId":"53e6a2664eda8036576f77eda5134fa7d3640f31","title":"Real-Time Influence Maximization on Dynamic Social Streams","url":"https://www.semanticscholar.org/paper/53e6a2664eda8036576f77eda5134fa7d3640f31","venue":"PVLDB","year":2017},{"arxivId":null,"authors":[{"authorId":"8766005","name":"Xiangyu Ke","url":"https://www.semanticscholar.org/author/8766005"},{"authorId":"1725060","name":"Arijit Khan","url":"https://www.semanticscholar.org/author/1725060"},{"authorId":"1737379","name":"Gao Cong","url":"https://www.semanticscholar.org/author/1737379"}],"doi":"10.1145/3183713.3199670","isInfluential":true,"paperId":"051afc077e4b3fa466641595d21c0fafc2b4c1d5","title":"Finding Seeds and Relevant Tags Jointly: For Targeted Influence Maximization in Social Networks","url":"https://www.semanticscholar.org/paper/051afc077e4b3fa466641595d21c0fafc2b4c1d5","venue":"SIGMOD Conference","year":2018},{"arxivId":null,"authors":[{"authorId":"2648734","name":"Mo Sha","url":"https://www.semanticscholar.org/author/2648734"},{"authorId":"2159885","name":"Yuchen Li","url":"https://www.semanticscholar.org/author/2159885"},{"authorId":"2220456","name":"Yanhao Wang","url":"https://www.semanticscholar.org/author/2220456"},{"authorId":"3393323","name":"Wentian Guo","url":"https://www.semanticscholar.org/author/3393323"},{"authorId":"1688848","name":"Kian-Lee Tan","url":"https://www.semanticscholar.org/author/1688848"}],"doi":"10.1109/icdmw.2018.00203","isInfluential":false,"paperId":"1fc74937ec85d618cc9c216b83e736f44965fea9","title":"River: A Real-Time Influence Monitoring System on Social Media Streams","url":"https://www.semanticscholar.org/paper/1fc74937ec85d618cc9c216b83e736f44965fea9","venue":"2018 IEEE International Conference on Data Mining Workshops (ICDMW)","year":2018}],"doi":"10.1145/3035918.3035952","influentialCitationCount":3,"paperId":"224e0bdb201a6953a5fc6ffec587d5963dcb0c29","references":[{"arxivId":null,"authors":[{"authorId":"1720384","name":"Vijay V. Vazirani","url":"https://www.semanticscholar.org/author/1720384"}],"doi":"10.1007/978-3-662-04565-7","isInfluential":false,"paperId":"107971a12550051421d4c570b3e9f285df09d6a8","title":"Approximation Algorithms","url":"https://www.semanticscholar.org/paper/107971a12550051421d4c570b3e9f285df09d6a8","venue":"Springer Berlin Heidelberg","year":2001},{"arxivId":null,"authors":[{"authorId":"1820049","name":"Surendra Sedhai","url":"https://www.semanticscholar.org/author/1820049"},{"authorId":"1735962","name":"Aixin Sun","url":"https://www.semanticscholar.org/author/1735962"}],"doi":"10.1145/2600428.2609452","isInfluential":false,"paperId":"41c8ff7475225c9dfe9cedc25c038e9216345cc6","title":"Hashtag recommendation for hyperlinked tweets","url":"https://www.semanticscholar.org/paper/41c8ff7475225c9dfe9cedc25c038e9216345cc6","venue":"SIGIR","year":2014},{"arxivId":null,"authors":[{"authorId":"1775511","name":"Meeyoung Cha","url":"https://www.semanticscholar.org/author/1775511"},{"authorId":"1763096","name":"Hamed Haddadi","url":"https://www.semanticscholar.org/author/1763096"},{"authorId":"1869561","name":"Fabr\u00edcio Benevenuto","url":"https://www.semanticscholar.org/author/1869561"},{"authorId":"1958921","name":"Krishna P. Gummadi","url":"https://www.semanticscholar.org/author/1958921"}],"doi":null,"isInfluential":false,"paperId":"1ad8410d0ded269af4a0116d8b38842a7549f0ae","title":"Measuring User Influence in Twitter: The Million Follower Fallacy","url":"https://www.semanticscholar.org/paper/1ad8410d0ded269af4a0116d8b38842a7549f0ae","venue":"ICWSM","year":2010},{"arxivId":null,"authors":[{"authorId":"2651864","name":"Cindy Xide Lin","url":"https://www.semanticscholar.org/author/2651864"},{"authorId":"1743469","name":"Qiaozhu Mei","url":"https://www.semanticscholar.org/author/1743469"},{"authorId":"1722175","name":"Jiawei Han","url":"https://www.semanticscholar.org/author/1722175"},{"authorId":"3247526","name":"Yunliang Jiang","url":"https://www.semanticscholar.org/author/3247526"},{"authorId":"1994333","name":"Marina Danilevsky","url":"https://www.semanticscholar.org/author/1994333"}],"doi":"10.1109/ICDM.2011.144","isInfluential":true,"paperId":"182dae04254e79a8cd6acee81114a686c8ca1cec","title":"The Joint Inference of Topic Diffusion and Evolution in Social Communities","url":"https://www.semanticscholar.org/paper/182dae04254e79a8cd6acee81114a686c8ca1cec","venue":"2011 IEEE 11th International Conference on Data Mining","year":2011},{"arxivId":null,"authors":[{"authorId":"1866985","name":"Youze Tang","url":"https://www.semanticscholar.org/author/1866985"},{"authorId":"2942571","name":"Yanchen Shi","url":"https://www.semanticscholar.org/author/2942571"},{"authorId":"33285410","name":"Xiaokui Xiao","url":"https://www.semanticscholar.org/author/33285410"}],"doi":"10.1145/2723372.2723734","isInfluential":false,"paperId":"706c83309fa09454a136d4e607364b27be66172c","title":"Influence Maximization in Near-Linear Time: A Martingale Approach","url":"https://www.semanticscholar.org/paper/706c83309fa09454a136d4e607364b27be66172c","venue":"SIGMOD Conference","year":2015},{"arxivId":null,"authors":[{"authorId":"1736632","name":"Jiliang Tang","url":"https://www.semanticscholar.org/author/1736632"},{"authorId":"1687568","name":"Xia Hu","url":"https://www.semanticscholar.org/author/1687568"},{"authorId":"38746648","name":"Huan Liu","url":"https://www.semanticscholar.org/author/38746648"}],"doi":"10.1007/s13278-013-0141-9","isInfluential":false,"paperId":"4cc352fa9dc7fc87389ce95e6779a2603f4ee87f","title":"Social recommendation: a review","url":"https://www.semanticscholar.org/paper/4cc352fa9dc7fc87389ce95e6779a2603f4ee87f","venue":"Social Network Analysis and Mining","year":2013},{"arxivId":null,"authors":[{"authorId":"40075113","name":"Sinead Williamson","url":"https://www.semanticscholar.org/author/40075113"},{"authorId":"40397541","name":"Chong Wang","url":"https://www.semanticscholar.org/author/40397541"},{"authorId":"3309269","name":"Katherine A. Heller","url":"https://www.semanticscholar.org/author/3309269"},{"authorId":"1796335","name":"David M. Blei","url":"https://www.semanticscholar.org/author/1796335"}],"doi":null,"isInfluential":false,"paperId":"a0bcdf26fcd382dd54ac38be07e6b33179bd52f4","title":"The IBP Compound Dirichlet Process and its Application to Focused Topic Modeling","url":"https://www.semanticscholar.org/paper/a0bcdf26fcd382dd54ac38be07e6b33179bd52f4","venue":"ICML","year":2010},{"arxivId":"1605.07990","authors":[{"authorId":"39433682","name":"Hung T. Nguyen","url":"https://www.semanticscholar.org/author/39433682"},{"authorId":"1698253","name":"My Tra Thai","url":"https://www.semanticscholar.org/author/1698253"},{"authorId":"1745290","name":"Thang N. Dinh","url":"https://www.semanticscholar.org/author/1745290"}],"doi":"10.1145/2882903.2915207","isInfluential":false,"paperId":"23d85a0008429845870780c6db3640c05165acaf","title":"Stop-and-Stare: Optimal Sampling Algorithms for Viral Marketing in Billion-scale Networks","url":"https://www.semanticscholar.org/paper/23d85a0008429845870780c6db3640c05165acaf","venue":"SIGMOD Conference","year":2016},{"arxivId":null,"authors":[{"authorId":"2873279","name":"Michalis Potamias","url":"https://www.semanticscholar.org/author/2873279"},{"authorId":"1705764","name":"Francesco Bonchi","url":"https://www.semanticscholar.org/author/1705764"},{"authorId":"1682878","name":"Aristides Gionis","url":"https://www.semanticscholar.org/author/1682878"},{"authorId":"1715771","name":"George Kollios","url":"https://www.semanticscholar.org/author/1715771"}],"doi":"10.14778/1920841.1920967","isInfluential":false,"paperId":"6eccbba04f448fa5bc93ed94bc63bb03d36e114c","title":"k-Nearest Neighbors in Uncertain Graphs","url":"https://www.semanticscholar.org/paper/6eccbba04f448fa5bc93ed94bc63bb03d36e114c","venue":"PVLDB","year":2010},{"arxivId":null,"authors":[{"authorId":"46479665","name":"Amit Goyal","url":"https://www.semanticscholar.org/author/46479665"},{"authorId":"1705764","name":"Francesco Bonchi","url":"https://www.semanticscholar.org/author/1705764"},{"authorId":"1708593","name":"Laks V. S. Lakshmanan","url":"https://www.semanticscholar.org/author/1708593"}],"doi":"10.1145/1718487.1718518","isInfluential":false,"paperId":"21968ae000669eb4cf03718a0d97e23a6bf75926","title":"Learning influence probabilities in social networks","url":"https://www.semanticscholar.org/paper/21968ae000669eb4cf03718a0d97e23a6bf75926","venue":"WSDM","year":2010},{"arxivId":null,"authors":[{"authorId":"50504401","name":"Wei Chen","url":"https://www.semanticscholar.org/author/50504401"},{"authorId":"46997388","name":"Tian Lin","url":"https://www.semanticscholar.org/author/46997388"},{"authorId":"3443627","name":"Cheng Yang","url":"https://www.semanticscholar.org/author/3443627"}],"doi":null,"isInfluential":false,"paperId":"fa4e93dbcdd1e4f20db9aeb34699a414420b7fd9","title":"Efficient Topic-aware Influence Maximization Using Preprocessing","url":"https://www.semanticscholar.org/paper/fa4e93dbcdd1e4f20db9aeb34699a414420b7fd9","venue":"ArXiv","year":2014},{"arxivId":null,"authors":[{"authorId":"5673974","name":"Mark S. Granovetter","url":"https://www.semanticscholar.org/author/5673974"}],"doi":null,"isInfluential":false,"paperId":"92b6aeb4e4f8e0c170f33ba274ce1830db9c9496","title":"Threshold Models of Collective Behavior !","url":"https://www.semanticscholar.org/paper/92b6aeb4e4f8e0c170f33ba274ce1830db9c9496","venue":"","year":2007},{"arxivId":null,"authors":[{"authorId":"3286520","name":"Andr\u00e1s A. Bencz\u00far","url":"https://www.semanticscholar.org/author/3286520"},{"authorId":"1743286","name":"David R. Karger","url":"https://www.semanticscholar.org/author/1743286"}],"doi":"10.1145/237814.237827","isInfluential":false,"paperId":"02678fe75012986ee59be79b628dd0e0cea0a9f1","title":"Approximating s-t Minimum Cuts in \u00d5(n2) Time","url":"https://www.semanticscholar.org/paper/02678fe75012986ee59be79b628dd0e0cea0a9f1","venue":"STOC","year":1996},{"arxivId":null,"authors":[{"authorId":"1765196","name":"David Kempe","url":"https://www.semanticscholar.org/author/1765196"},{"authorId":"3371403","name":"Jon M. Kleinberg","url":"https://www.semanticscholar.org/author/3371403"},{"authorId":"1746222","name":"\u00c9va Tardos","url":"https://www.semanticscholar.org/author/1746222"}],"doi":"10.4086/toc.2015.v011a004","isInfluential":true,"paperId":"b790f9ae49cdee5354eacfc7897ab9752acd5e2a","title":"Maximizing the Spread of Influence through a Social Network","url":"https://www.semanticscholar.org/paper/b790f9ae49cdee5354eacfc7897ab9752acd5e2a","venue":"Theory of Computing","year":2015},{"arxivId":"1404.0900","authors":[{"authorId":"1866985","name":"Youze Tang","url":"https://www.semanticscholar.org/author/1866985"},{"authorId":"33285410","name":"Xiaokui Xiao","url":"https://www.semanticscholar.org/author/33285410"},{"authorId":"2942571","name":"Yanchen Shi","url":"https://www.semanticscholar.org/author/2942571"}],"doi":"10.1145/2588555.2593670","isInfluential":true,"paperId":"abb152802d5b4686a394e221abe951187ea06158","title":"Influence maximization: near-optimal time complexity meets practical efficiency","url":"https://www.semanticscholar.org/paper/abb152802d5b4686a394e221abe951187ea06158","venue":"SIGMOD Conference","year":2014},{"arxivId":null,"authors":[{"authorId":"1796335","name":"David M. Blei","url":"https://www.semanticscholar.org/author/1796335"},{"authorId":"1701538","name":"Andrew Y. Ng","url":"https://www.semanticscholar.org/author/1701538"},{"authorId":"1694621","name":"Michael I. Jordan","url":"https://www.semanticscholar.org/author/1694621"}],"doi":null,"isInfluential":true,"paperId":"1e56ed3d2c855f848ffd91baa90f661772a279e1","title":"Latent Dirichlet Allocation","url":"https://www.semanticscholar.org/paper/1e56ed3d2c855f848ffd91baa90f661772a279e1","venue":"NIPS","year":2003},{"arxivId":null,"authors":[{"authorId":"39423578","name":"Jianxiu Hao","url":"https://www.semanticscholar.org/author/39423578"},{"authorId":"1795576","name":"James B. Orlin","url":"https://www.semanticscholar.org/author/1795576"}],"doi":"10.1006/jagm.1994.1043","isInfluential":false,"paperId":"2ee8c773ef22776b0113c78325ca76b701cbb78e","title":"A Faster Algorithm for Finding the Minimum Cut in a Directed Graph","url":"https://www.semanticscholar.org/paper/2ee8c773ef22776b0113c78325ca76b701cbb78e","venue":"J. Algorithms","year":1994},{"arxivId":null,"authors":[{"authorId":"1744007","name":"Gediminas Adomavicius","url":"https://www.semanticscholar.org/author/1744007"},{"authorId":"1680593","name":"Alexander Tuzhilin","url":"https://www.semanticscholar.org/author/1680593"}],"doi":"10.1109/TKDE.2005.99","isInfluential":false,"paperId":"3cbcd163a1a398d9b22c8b85f993e3c62bbd3701","title":"Toward the next generation of recommender systems: a survey of the state-of-the-art and possible extensions","url":"https://www.semanticscholar.org/paper/3cbcd163a1a398d9b22c8b85f993e3c62bbd3701","venue":"IEEE Transactions on Knowledge and Data Engineering","year":2005},{"arxivId":null,"authors":[{"authorId":"31631336","name":"Aaron Q. Li","url":"https://www.semanticscholar.org/author/31631336"},{"authorId":"2147739","name":"Amr Ahmed","url":"https://www.semanticscholar.org/author/2147739"},{"authorId":"35014893","name":"Sujith Ravi","url":"https://www.semanticscholar.org/author/35014893"},{"authorId":"1691629","name":"Alexander J. Smola","url":"https://www.semanticscholar.org/author/1691629"}],"doi":"10.1145/2623330.2623756","isInfluential":false,"paperId":"137aec8c56102cea1ac7c083989036bb51331fdc","title":"Reducing the sampling complexity of topic models","url":"https://www.semanticscholar.org/paper/137aec8c56102cea1ac7c083989036bb51331fdc","venue":"KDD","year":2014},{"arxivId":null,"authors":[{"authorId":"1841048","name":"Fr\u00e9deric Godin","url":"https://www.semanticscholar.org/author/1841048"},{"authorId":"2688354","name":"Viktor Slavkovikj","url":"https://www.semanticscholar.org/author/2688354"},{"authorId":"7627712","name":"Wesley De Neve","url":"https://www.semanticscholar.org/author/7627712"},{"authorId":"2621946","name":"Benjamin Schrauwen","url":"https://www.semanticscholar.org/author/2621946"},{"authorId":"1718333","name":"Rik Van de Walle","url":"https://www.semanticscholar.org/author/1718333"}],"doi":"10.1145/2487788.2488002","isInfluential":true,"paperId":"239c6ebf6172f8f34e9d103ca1c10056d532be09","title":"Using topic models for Twitter hashtag recommendation","url":"https://www.semanticscholar.org/paper/239c6ebf6172f8f34e9d103ca1c10056d532be09","venue":"WWW","year":2013},{"arxivId":null,"authors":[{"authorId":"4231116","name":"Fan R. K. Chung","url":"https://www.semanticscholar.org/author/4231116"},{"authorId":"1705789","name":"Linyuan Lu","url":"https://www.semanticscholar.org/author/1705789"}],"doi":null,"isInfluential":false,"paperId":"6be7b1817e67a773d7f17601d7bf6024b81435a8","title":"Concentration inequalities and martingale inequalities \u2014 a survey","url":"https://www.semanticscholar.org/paper/6be7b1817e67a773d7f17601d7bf6024b81435a8","venue":"","year":2005},{"arxivId":null,"authors":[{"authorId":"1775627","name":"Aaditeshwar Seth","url":"https://www.semanticscholar.org/author/1775627"},{"authorId":"36611093","name":"Jie Zhang","url":"https://www.semanticscholar.org/author/36611093"}],"doi":null,"isInfluential":false,"paperId":"33679dcb1fa8873c7be583c45cd9982cd73b5db3","title":"A Social Network Based Approach to Personalized Recommendation of Participatory Media Content","url":"https://www.semanticscholar.org/paper/33679dcb1fa8873c7be583c45cd9982cd73b5db3","venue":"ICWSM","year":2008},{"arxivId":null,"authors":[{"authorId":"1725060","name":"Arijit Khan","url":"https://www.semanticscholar.org/author/1725060"},{"authorId":"1705764","name":"Francesco Bonchi","url":"https://www.semanticscholar.org/author/1705764"},{"authorId":"1682878","name":"Aristides Gionis","url":"https://www.semanticscholar.org/author/1682878"},{"authorId":"1794262","name":"Francesco Gullo","url":"https://www.semanticscholar.org/author/1794262"}],"doi":"10.5441/002/edbt.2014.48","isInfluential":false,"paperId":"0a888fadf7f8ac8eb0f194f7979e421ce072bcc4","title":"Fast Reliability Search in Uncertain Graphs","url":"https://www.semanticscholar.org/paper/0a888fadf7f8ac8eb0f194f7979e421ce072bcc4","venue":"EDBT","year":2014},{"arxivId":null,"authors":[{"authorId":"1687630","name":"Kerui Min","url":"https://www.semanticscholar.org/author/1687630"},{"authorId":"48805472","name":"Zhengdong Zhang","url":"https://www.semanticscholar.org/author/48805472"},{"authorId":"47583369","name":"John N. Wright","url":"https://www.semanticscholar.org/author/47583369"},{"authorId":"50032052","name":"Yi Ma","url":"https://www.semanticscholar.org/author/50032052"}],"doi":"10.1145/1871437.1871475","isInfluential":false,"paperId":"1de0168bb79272d3faafdcda5c9bb4b2a00a15d8","title":"Decomposing background topics from keywords by principal component pursuit","url":"https://www.semanticscholar.org/paper/1de0168bb79272d3faafdcda5c9bb4b2a00a15d8","venue":"CIKM","year":2010},{"arxivId":null,"authors":[{"authorId":"13436774","name":"Jie Tang","url":"https://www.semanticscholar.org/author/13436774"},{"authorId":"1738536","name":"Jimeng Sun","url":"https://www.semanticscholar.org/author/1738536"},{"authorId":"48586386","name":"Chi Wang","url":"https://www.semanticscholar.org/author/48586386"},{"authorId":"50109422","name":"Zi Yang","url":"https://www.semanticscholar.org/author/50109422"}],"doi":"10.1145/1557019.1557108","isInfluential":false,"paperId":"1339b888fb739b8a1194fa94fbe848e01d93456a","title":"Social influence analysis in large-scale networks","url":"https://www.semanticscholar.org/paper/1339b888fb739b8a1194fa94fbe848e01d93456a","venue":"KDD","year":2009},{"arxivId":null,"authors":[{"authorId":"1702139","name":"Jure Leskovec","url":"https://www.semanticscholar.org/author/1702139"},{"authorId":"1734448","name":"Andreas Krause","url":"https://www.semanticscholar.org/author/1734448"},{"authorId":"1730156","name":"Carlos Guestrin","url":"https://www.semanticscholar.org/author/1730156"},{"authorId":"1702392","name":"Christos Faloutsos","url":"https://www.semanticscholar.org/author/1702392"},{"authorId":"3009469","name":"Jeanne M. VanBriesen","url":"https://www.semanticscholar.org/author/3009469"},{"authorId":"1726974","name":"Natalie S. Glance","url":"https://www.semanticscholar.org/author/1726974"}],"doi":"10.1145/1281192.1281239","isInfluential":false,"paperId":"4cd73382dc17561cd276f276c61d5ebf39bf69ad","title":"Cost-effective outbreak detection in networks","url":"https://www.semanticscholar.org/paper/4cd73382dc17561cd276f276c61d5ebf39bf69ad","venue":"KDD","year":2007},{"arxivId":null,"authors":[{"authorId":"1721812","name":"Christian Borgs","url":"https://www.semanticscholar.org/author/1721812"},{"authorId":"1769877","name":"Mickey Brautbar","url":"https://www.semanticscholar.org/author/1769877"},{"authorId":"1695997","name":"Jennifer T. Chayes","url":"https://www.semanticscholar.org/author/1695997"},{"authorId":"1694393","name":"Brendan Lucier","url":"https://www.semanticscholar.org/author/1694393"}],"doi":null,"isInfluential":false,"paperId":"89927a37854b2d479cf7ae51016faed9222a14ed","title":"Influence Maximization in Social Networks: Towards an Optimal Algorithmic Solution","url":"https://www.semanticscholar.org/paper/89927a37854b2d479cf7ae51016faed9222a14ed","venue":"ArXiv","year":2012},{"arxivId":null,"authors":[{"authorId":"103045882","name":"Morteza Aalabaf\u2010Sabaghi","url":"https://www.semanticscholar.org/author/103045882"}],"doi":"10.1111/j.1467-985X.2012.01069_4.x","isInfluential":false,"paperId":"f0a6f060af064e906bfde8d166f7a00544653a9b","title":"Networks, Crowds and Markets: Reasoning about a Highly Connected World","url":"https://www.semanticscholar.org/paper/f0a6f060af064e906bfde8d166f7a00544653a9b","venue":"","year":2012},{"arxivId":null,"authors":[{"authorId":"1723035","name":"Matthias Renz","url":"https://www.semanticscholar.org/author/1723035"},{"authorId":"1966497","name":"Reynold Cheng","url":"https://www.semanticscholar.org/author/1966497"},{"authorId":"1688561","name":"Hans-Peter Kriegel","url":"https://www.semanticscholar.org/author/1688561"},{"authorId":"3221975","name":"Andreas Z\u00fcfle","url":"https://www.semanticscholar.org/author/3221975"},{"authorId":"3049466","name":"Thomas Bernecker","url":"https://www.semanticscholar.org/author/3049466"}],"doi":"10.14778/1920841.1921066","isInfluential":false,"paperId":"81aa239cb8f106a379f7571ac7b1498fb58ec712","title":"Similarity Search and Mining in Uncertain Databases","url":"https://www.semanticscholar.org/paper/81aa239cb8f106a379f7571ac7b1498fb58ec712","venue":"PVLDB","year":2010},{"arxivId":null,"authors":[{"authorId":"32103099","name":"Inbal Ronen","url":"https://www.semanticscholar.org/author/32103099"},{"authorId":"1750703","name":"Ido Guy","url":"https://www.semanticscholar.org/author/1750703"},{"authorId":"1681183","name":"Elad Kravi","url":"https://www.semanticscholar.org/author/1681183"},{"authorId":"7858406","name":"Maya Barnea","url":"https://www.semanticscholar.org/author/7858406"}],"doi":"10.1145/2600428.2609596","isInfluential":false,"paperId":"0b95749c8751d46c3a15735e914ccc1e0f8590af","title":"Recommending social media content to community owners","url":"https://www.semanticscholar.org/paper/0b95749c8751d46c3a15735e914ccc1e0f8590af","venue":"SIGIR","year":2014},{"arxivId":null,"authors":[{"authorId":"39802490","name":"Lu Liu","url":"https://www.semanticscholar.org/author/39802490"},{"authorId":"13436774","name":"Jie Tang","url":"https://www.semanticscholar.org/author/13436774"},{"authorId":"1722175","name":"Jiawei Han","url":"https://www.semanticscholar.org/author/1722175"},{"authorId":"41092463","name":"Meng Jiang","url":"https://www.semanticscholar.org/author/41092463"},{"authorId":"1689674","name":"Shiqiang Yang","url":"https://www.semanticscholar.org/author/1689674"}],"doi":"10.1145/1871437.1871467","isInfluential":true,"paperId":"2e9b18872712817e5d98bc54ea6ee8a7bd66fbeb","title":"Mining topic-level influence in heterogeneous networks","url":"https://www.semanticscholar.org/paper/2e9b18872712817e5d98bc54ea6ee8a7bd66fbeb","venue":"CIKM","year":2010},{"arxivId":null,"authors":[{"authorId":"1740308","name":"Ruoming Jin","url":"https://www.semanticscholar.org/author/1740308"},{"authorId":"38495716","name":"Lin Liu","url":"https://www.semanticscholar.org/author/38495716"},{"authorId":"1696332","name":"Bolin Ding","url":"https://www.semanticscholar.org/author/1696332"},{"authorId":"1745000","name":"Haixun Wang","url":"https://www.semanticscholar.org/author/1745000"}],"doi":"10.14778/2002938.2002941","isInfluential":false,"paperId":"404d38143b1078fcb4329f6addbd781d2a99f9b0","title":"Distance-Constraint Reachability Computation in Uncertain Graphs","url":"https://www.semanticscholar.org/paper/404d38143b1078fcb4329f6addbd781d2a99f9b0","venue":"PVLDB","year":2011},{"arxivId":null,"authors":[{"authorId":"1694591","name":"Nicola Barbieri","url":"https://www.semanticscholar.org/author/1694591"},{"authorId":"1705764","name":"Francesco Bonchi","url":"https://www.semanticscholar.org/author/1705764"},{"authorId":"1718485","name":"Giuseppe Manco","url":"https://www.semanticscholar.org/author/1718485"}],"doi":"10.1007/s10115-013-0646-6","isInfluential":true,"paperId":"1f559f2eb174d05a912b2ec39a48eadfd0160b74","title":"Topic-aware social influence propagation models","url":"https://www.semanticscholar.org/paper/1f559f2eb174d05a912b2ec39a48eadfd0160b74","venue":"Knowledge and Information Systems","year":2012},{"arxivId":null,"authors":[{"authorId":"39661133","name":"Wei Chen","url":"https://www.semanticscholar.org/author/39661133"},{"authorId":"48586386","name":"Chi Wang","url":"https://www.semanticscholar.org/author/48586386"},{"authorId":"47905107","name":"Yajun Wang","url":"https://www.semanticscholar.org/author/47905107"}],"doi":"10.1145/1835804.1835934","isInfluential":true,"paperId":"28bf0df09f97e7ef9108e71b45fe1b9a7aa201e2","title":"Scalable influence maximization for prevalent viral marketing in large-scale social networks","url":"https://www.semanticscholar.org/paper/28bf0df09f97e7ef9108e71b45fe1b9a7aa201e2","venue":"KDD","year":2010},{"arxivId":"1502.03630","authors":[{"authorId":"48857157","name":"Min Yang","url":"https://www.semanticscholar.org/author/48857157"},{"authorId":"13077228","name":"Tianyi Cui","url":"https://www.semanticscholar.org/author/13077228"},{"authorId":"1680761","name":"Wenting Tu","url":"https://www.semanticscholar.org/author/1680761"}],"doi":null,"isInfluential":false,"paperId":"360a12e2f5c56e53cc97007678ee97dd85ecef14","title":"Ordering-sensitive and Semantic-aware Topic Modeling","url":"https://www.semanticscholar.org/paper/360a12e2f5c56e53cc97007678ee97dd85ecef14","venue":"AAAI","year":2015},{"arxivId":null,"authors":[{"authorId":"19309380","name":"Shuo Chen","url":"https://www.semanticscholar.org/author/19309380"},{"authorId":"3232294","name":"Ju Fan","url":"https://www.semanticscholar.org/author/3232294"},{"authorId":"23492509","name":"Guoliang Li","url":"https://www.semanticscholar.org/author/23492509"},{"authorId":"33091680","name":"Jianhua Feng","url":"https://www.semanticscholar.org/author/33091680"},{"authorId":"1688848","name":"Kian-Lee Tan","url":"https://www.semanticscholar.org/author/1688848"},{"authorId":"8053308","name":"Jinhui Tang","url":"https://www.semanticscholar.org/author/8053308"}],"doi":"10.14778/2735703.2735706","isInfluential":true,"paperId":"084419435227a5bbf54d47ba54e11739756510fd","title":"Online Topic-Aware Influence Maximization","url":"https://www.semanticscholar.org/paper/084419435227a5bbf54d47ba54e11739756510fd","venue":"PVLDB","year":2015},{"arxivId":null,"authors":[{"authorId":"1895150","name":"Paul Dagum","url":"https://www.semanticscholar.org/author/1895150"},{"authorId":"1739801","name":"Richard M. Karp","url":"https://www.semanticscholar.org/author/1739801"},{"authorId":"1720237","name":"Michael Luby","url":"https://www.semanticscholar.org/author/1720237"},{"authorId":"2352366","name":"Sheldon M. Ross","url":"https://www.semanticscholar.org/author/2352366"}],"doi":"10.1137/S0097539797315306","isInfluential":false,"paperId":"8c1fa3949409eb65017a4625a7351039f72ebf04","title":"An Optimal Algorithm for Monte Carlo Estimation","url":"https://www.semanticscholar.org/paper/8c1fa3949409eb65017a4625a7351039f72ebf04","venue":"SIAM J. Comput.","year":2000},{"arxivId":null,"authors":[{"authorId":"39578728","name":"Kun Xu","url":"https://www.semanticscholar.org/author/39578728"},{"authorId":"38417991","name":"Lei Zou","url":"https://www.semanticscholar.org/author/38417991"},{"authorId":"1718849","name":"Jeffrey Xu Yu","url":"https://www.semanticscholar.org/author/1718849"},{"authorId":"37833805","name":"Lei Chen","url":"https://www.semanticscholar.org/author/37833805"},{"authorId":"3011950","name":"Yanghua Xiao","url":"https://www.semanticscholar.org/author/3011950"},{"authorId":"1791036","name":"Dongyan Zhao","url":"https://www.semanticscholar.org/author/1791036"}],"doi":"10.1145/2063576.2063807","isInfluential":false,"paperId":"43a068652277ca9213202d984a69965e7fec5dd9","title":"Answering label-constraint reachability in large graphs","url":"https://www.semanticscholar.org/paper/43a068652277ca9213202d984a69965e7fec5dd9","venue":"CIKM","year":2011},{"arxivId":null,"authors":[{"authorId":"3222408","name":"\u00c7igdem Aslay","url":"https://www.semanticscholar.org/author/3222408"},{"authorId":"1694591","name":"Nicola Barbieri","url":"https://www.semanticscholar.org/author/1694591"},{"authorId":"1705764","name":"Francesco Bonchi","url":"https://www.semanticscholar.org/author/1705764"},{"authorId":"1747635","name":"Ricardo A. Baeza-Yates","url":"https://www.semanticscholar.org/author/1747635"}],"doi":"10.5441/002/edbt.2014.28","isInfluential":true,"paperId":"50ef0cbcc318ec98c7d6132b9c539e9cf41db010","title":"Online Topic-aware Influence Maximization Queries","url":"https://www.semanticscholar.org/paper/50ef0cbcc318ec98c7d6132b9c539e9cf41db010","venue":"EDBT","year":2014},{"arxivId":null,"authors":[{"authorId":"1740308","name":"Ruoming Jin","url":"https://www.semanticscholar.org/author/1740308"},{"authorId":"49166462","name":"Hui Hong","url":"https://www.semanticscholar.org/author/49166462"},{"authorId":"1745000","name":"Haixun Wang","url":"https://www.semanticscholar.org/author/1745000"},{"authorId":"1784100","name":"Ning Ruan","url":"https://www.semanticscholar.org/author/1784100"},{"authorId":"1730821","name":"Y. C. Xiang","url":"https://www.semanticscholar.org/author/1730821"}],"doi":"10.1145/1807167.1807183","isInfluential":false,"paperId":"6f8a2339aabb699d8810baed2564744ca837f009","title":"Computing label-constraint reachability in graph databases","url":"https://www.semanticscholar.org/paper/6f8a2339aabb699d8810baed2564744ca837f009","venue":"SIGMOD Conference","year":2010},{"arxivId":null,"authors":[{"authorId":"1750484","name":"Frank Harary","url":"https://www.semanticscholar.org/author/1750484"},{"authorId":"2458887","name":"Lester Randolph Ford","url":"https://www.semanticscholar.org/author/2458887"},{"authorId":"2093820","name":"Delbert Ray Fulkerson","url":"https://www.semanticscholar.org/author/2093820"}],"doi":"10.2307/2311955","isInfluential":false,"paperId":"a9f4bb33e5e9fd0d4a1193deb3d4459adbb82c35","title":"Flows in Networks.","url":"https://www.semanticscholar.org/paper/a9f4bb33e5e9fd0d4a1193deb3d4459adbb82c35","venue":"","year":1964}],"title":"Discovering Your Selling Points: Personalized Social Influential Tags Exploration","topics":[{"topic":"Sampling (signal processing)","topicId":"7839","url":"https://www.semanticscholar.org/topic/7839"},{"topic":"Personalization","topicId":"2873","url":"https://www.semanticscholar.org/topic/2873"},{"topic":"Approximation algorithm","topicId":"87","url":"https://www.semanticscholar.org/topic/87"},{"topic":"Social network","topicId":"12426","url":"https://www.semanticscholar.org/topic/12426"},{"topic":"Best-effort delivery","topicId":"112430","url":"https://www.semanticscholar.org/topic/112430"},{"topic":"NP-hardness","topicId":"4143","url":"https://www.semanticscholar.org/topic/4143"},{"topic":"NP (complexity)","topicId":"3594787","url":"https://www.semanticscholar.org/topic/3594787"},{"topic":"Performance","topicId":"3097","url":"https://www.semanticscholar.org/topic/3097"},{"topic":"Computation","topicId":"339","url":"https://www.semanticscholar.org/topic/339"},{"topic":"Experiment","topicId":"378","url":"https://www.semanticscholar.org/topic/378"},{"topic":"Speedup","topicId":"4162","url":"https://www.semanticscholar.org/topic/4162"},{"topic":"Lazy evaluation","topicId":"19479","url":"https://www.semanticscholar.org/topic/19479"},{"topic":"Software propagation","topicId":"2021211","url":"https://www.semanticscholar.org/topic/2021211"}],"url":"https://www.semanticscholar.org/paper/224e0bdb201a6953a5fc6ffec587d5963dcb0c29","venue":"SIGMOD Conference","year":2017}
